gitsplit/config.py
gitsplit/git.py
gitsplit/log.py
gitsplit/main.py
gitsplit/split.py
git_split-0.0.1.dist-info/entry_points.txt
git_split-0.0.1.dist-info/LICENSE
git_split-0.0.1.dist-info/WHEEL
git_split-0.0.1.dist-info/METADATA
git_split-0.0.1.dist-info/RECORD
