Metadata-Version: 2.1
Name: git-split
Version: 0.0.1
Summary: A history-preserving file splitter for Git.
License: MIT
Author: Eric Smith
Author-email: eric@esmithy.net
Requires-Python: >=3.6,<4.0
Classifier: License :: OSI Approved :: MIT License
Classifier: Programming Language :: Python :: 3
Classifier: Programming Language :: Python :: 3.6
Classifier: Programming Language :: Python :: 3.7
Classifier: Programming Language :: Python :: 3.8
Requires-Dist: python-ranges (>=0.1.3,<0.2.0)
Requires-Dist: toml (>=0.10.0,<0.11.0)
